pycimg/__init__.py
pycimg/cimg_bindings.cpython-311-darwin.so
pycimg/pycimg.py
pycimg/.dylibs/libxcb.1.dylib
pycimg/.dylibs/libX11.6.dylib
pycimg/.dylibs/libpng16.16.dylib
pycimg/.dylibs/libXau.6.dylib
pycimg-2.0.2.dist-info/RECORD
pycimg-2.0.2.dist-info/LICENSE
pycimg-2.0.2.dist-info/WHEEL
pycimg-2.0.2.dist-info/top_level.txt
pycimg-2.0.2.dist-info/METADATA
